yesig/__init__.py
yesig/messages.py
yesig/siginterface.py
yesig-0.1.0.dist-info/METADATA
yesig-0.1.0.dist-info/WHEEL
yesig-0.1.0.dist-info/licenses/LICENSE
yesig-0.1.0.dist-info/RECORD
