Metadata-Version: 2.4
Name: yesig
Version: 0.1.0
Summary: A simple python interface for the signal-cli rest api. With support for the json-rpc websocket via asyncio
Author-email: DJ_Pigeon <dj_pigeon030@protonmail.com>
License-Expression: MIT
License-File: LICENSE
Classifier: Operating System :: OS Independent
Classifier: Programming Language :: Python :: 3
Requires-Python: >=3.14.2
Requires-Dist: requests
Provides-Extra: rpcsupport
Requires-Dist: websockets; extra == 'rpcsupport'
